{"votes":[{"time":1691172129,"choices":[7,6,4,1,2],"user":"473557600009584640"},{"time":1691181101,"choices":[5,6,7],"user":"978097312263974962"},{"time":1691181888,"choices":[1,2,3,4,5,7],"user":"338450543401893888"},{"time":1691202983,"choices":[1,2,3,7],"user":"519471129577127937"},{"time":1691220008,"choices":[2,3,4,5,6,7],"user":"145356438401843201"},{"time":1691251585,"choices":[6],"user":"540897372700409868"},{"time":1691256065,"choices":[2,4,3,7,1],"user":"718108253657235487"}],"suggestions":{"145356438401843201":"https://anilist.co/manga/67109/Yokokuhan/","540897372700409868":"https://anilist.co/manga/34625/The-Summit-of-the-Gods/","772008147384008735":"https://anilist.co/manga/65573/orange/","519471129577127937":"https://anilist.co/manga/60779/Tetsugaku-Letra/","running":false,"718108253657235487":"https://anilist.co/manga/85138/ib-Instant-Bullet/","338450543401893888":"https://anilist.co/manga/86639/Koi-wa-Ameagari-no-You-ni/","554371090315476992":"https://anilist.co/manga/98689/Kings-Maker/"},"genre_cooldown":["School Life","Fantasy","Mystery","Ecchi","Supernatural","Sports","Drama","Yaoi/Shounen Ai"],"choices":{"links":["https://anilist.co/manga/67109/Yokokuhan/","https://anilist.co/manga/34625/The-Summit-of-the-Gods/","https://anilist.co/manga/65573/orange/","https://anilist.co/manga/60779/Tetsugaku-Letra/","https://anilist.co/manga/85138/ib-Instant-Bullet/","https://anilist.co/manga/86639/Koi-wa-Ameagari-no-You-ni/","https://anilist.co/manga/98689/Kings-Maker/"],"running":true,"names":["Yokokuhan","The Summit of the Gods","orange","Tetsugaku Letra","ib Instant Bullet","Koi wa Ameagari no You ni","Kings Maker"]}}